lazimp/__init__.py
lazimp-0.0.5.dist-info/LICENSE
lazimp-0.0.5.dist-info/METADATA
lazimp-0.0.5.dist-info/WHEEL
lazimp-0.0.5.dist-info/top_level.txt
lazimp-0.0.5.dist-info/RECORD
