Metadata-Version: 2.1
Name: lazimp
Version: 0.0.5
Summary: LazImp, the package for lazy import of packages, modules and symboles
Author-email: Dorian Turba <lazimp.pip.drd8f@8shield.net>
Project-URL: Homepage, https://github.com/dorianturba/lazimport
Project-URL: Bug Tracker, https://github.com/dorianturba/lazimport/issues
Classifier: Programming Language :: Python :: 3
Classifier: License :: OSI Approved :: MIT License
Classifier: Operating System :: OS Independent
Classifier: Development Status :: 3 - Alpha
Classifier: Programming Language :: Python :: 3.10
Classifier: Programming Language :: Python :: 3.11
Requires-Python: >=3.10
License-File: LICENSE
